BeautifullTerminal/__init__.py
BeautifullTerminal/terminal.py
beautifull_terminal-1.9.18.dist-info/LICENSE
beautifull_terminal-1.9.18.dist-info/METADATA
beautifull_terminal-1.9.18.dist-info/WHEEL
beautifull_terminal-1.9.18.dist-info/top_level.txt
beautifull_terminal-1.9.18.dist-info/RECORD
