Metadata-Version: 2.2
Name: beautifull-terminal
Version: 1.9.18
Summary: Automatically beautify your terminal output with colors.
Home-page: https://github.com/StarGames2025/beautifull_terminal
Author: starcrusher2025
Keywords: terminal,color,beautify,print
Classifier: Programming Language :: Python :: 3
Classifier: License :: OSI Approved :: MIT License
Classifier: Operating System :: OS Independent
Classifier: Programming Language :: Python :: 3.12
Requires-Python: >=3.6
License-File: LICENSE
Requires-Dist: setuptools
Provides-Extra: versionshelper
Requires-Dist: requests; extra == "versionshelper"
Requires-Dist: pkg_resources; extra == "versionshelper"
Dynamic: author
Dynamic: classifier
Dynamic: description
Dynamic: description-content-type
Dynamic: home-page
Dynamic: keywords
Dynamic: provides-extra
Dynamic: requires-dist
Dynamic: requires-python
Dynamic: summary
